marvinhelp/__init__.py
marvinhelp/marvinhelp.py
marvinhelp-0.1.4.data/scripts/marvin-advice
marvinhelp-0.1.4.dist-info/DESCRIPTION.rst
marvinhelp-0.1.4.dist-info/METADATA
marvinhelp-0.1.4.dist-info/RECORD
marvinhelp-0.1.4.dist-info/WHEEL
marvinhelp-0.1.4.dist-info/metadata.json
marvinhelp-0.1.4.dist-info/top_level.txt
