Metadata-Version: 2.0
Name: marvinhelp
Version: 0.1.4
Summary: Unhelpful advice from a very smart robot.
Home-page: https://github.com/rolfantlers
Author: Anders Amundson
Author-email: amundson@gmail.com
License: MIT
Keywords: nonsense,robots,advice
Platform: UNKNOWN
Requires-Python: >=3
Requires-Dist: nose
